[
  {
    "codigo": "INF3240",
    "nombre": "Programaci칩n Avanzada",
    "horasCatedra": 4,
    "horasLaboratorio": 2,
    "nivel": 3,
    "esAtemporal": false,
    "esCursoGeneral": false,
    "cantidadDeEstudiantes": 30
  },
  {
    "codigo": "MAT1010",
    "nombre": "C치lculo I",
    "horasCatedra": 6,
    "horasLaboratorio": 0,
    "nivel": 1,
    "esAtemporal": false,
    "esCursoGeneral": true,
    "cantidadDeEstudiantes": 45
  },
  {
    "codigo": "INF113",
    "nombre": "Introducci칩n a la Computaci칩n 1",
    "horasCatedra": 6,
    "horasLaboratorio": 0,
    "nivel": 1,
    "esAtemporal": false,
    "esCursoGeneral": true,
    "cantidadDeEstudiantes": 45
  }
] 